modeller/__init__.py
modeller/make_model.py
modeller/past_make_model.py
modeller/support.py
modeller-0.1.1.dist-info/METADATA
modeller-0.1.1.dist-info/WHEEL
modeller-0.1.1.dist-info/top_level.txt
modeller-0.1.1.dist-info/RECORD
