Metadata-Version: 2.1
Name: modeller
Version: 0.1.1
Summary: create efficent models starting from json schema
Home-page: https://github.com/rpc-botnets/instagram-botnet
Author: Tommaso De Rossi
Author-email: daer.tommy@gmail.com
License: Apache Software License 2.0
Keywords: model,schema,structure,struct,abstarct
Platform: UNKNOWN
Classifier: Intended Audience :: Information Technology
Classifier: License :: OSI Approved :: Apache Software License
Classifier: Programming Language :: Python :: 3
Classifier: Programming Language :: Python :: 3.6
Classifier: Programming Language :: Python :: 3.7
Requires-Dist: fastjsonschema
